{"sections":{"main":{"type":"main-page","disabled":true,"settings":{"padding_top":28,"padding_bottom":28}},"16474139196fbe8f11":{"type":"featured-media","blocks":{"7e5129ef-5e34-4840-804d-9a11477c4b78":{"type":"signup","settings":{"klaviyo_list_id":"Tzqmmq","show_email_input":true,"label_email":"Email","placeholder_email":"your@email.com","show_phone_input":false,"label_phone":"Phone","placeholder_phone":"323-000-0000"}}},"block_order":["7e5129ef-5e34-4840-804d-9a11477c4b78"],"settings":{"section_style":"light","section_bg_color":"#fff8e8","section_max_width":100,"section_height":"adapt","media_position":"normal","reverse_mobile":true,"media_size":"medium","padding_top":0,"padding_bottom":0,"media_type":"use_image","section_image":"shopify:\/\/shop_images\/Group-1.jpg","autoplay":true,"loop":true,"muted":true,"playsinline":true,"autobuffer":true,"preload":true,"controls":false,"video_url":"","media_margin_left":0,"media_margin_right":0,"enable_max_media_width":true,"max_media_width":100,"content_max_width":800,"text_position":"left","text_position_mobile":"left","content_padding_desktop":"p60","content_padding_mobile":"m-p20","section_title":"SIGN UP TO WIN — THE CIRO ESTELLE TENNIS BRACELET","title_font_size":24,"heading_style":"bold","section_paragraph":"<p>A new site, a new CIRO: in commemoration and celebration, we’re giving those new to our century-old brand the chance to win the stately Estelle Tennis Bracelet – sterling silver, white gold plated, & set with white CIROlite – absolutely free. Drawing announced via email. <\/p><p><\/p><p>All who enter will receive a $50 credit and early access to the new shop upon launch – our welcome to you for joining the CIRO community!<\/p>","text_font_size":15,"text_style":"medium","section_button_text":"Shop Now","section_url":"","button_style":"primary","enable_footer":false}}},"order":["main","16474139196fbe8f11"]}